rda_ispd_python/__init__.py
rda_ispd_python/ispd_common.py
rda_ispd_python/ispddb.py
rda_ispd_python/ispddb_config.py
rda_ispd_python-1.0.2.dist-info/LICENSE
rda_ispd_python-1.0.2.dist-info/METADATA
rda_ispd_python-1.0.2.dist-info/WHEEL
rda_ispd_python-1.0.2.dist-info/top_level.txt
rda_ispd_python-1.0.2.dist-info/RECORD
